setup.py
awsml_probability/Binomialdistribution.py
awsml_probability/Gaussiandistribution.py
awsml_probability/Generaldistribution.py
awsml_probability/__init__.py
awsml_probability.egg-info/PKG-INFO
awsml_probability.egg-info/SOURCES.txt
awsml_probability.egg-info/dependency_links.txt
awsml_probability.egg-info/not-zip-safe
awsml_probability.egg-info/top_level.txt