Metadata-Version: 1.0
Name: awsml-probability
Version: 0.1
Summary: Gaussian and Binomial distributions
Home-page: UNKNOWN
Author: Jung Soon Noh
Author-email: gracewm892@gmail.com
License: UNKNOWN
Platform: UNKNOWN
